[
  {
    "title":"Java 11",
    "image":"/logos/java.svg",
    "link":"https://www.oracle.com/ca-en/java/"
  },
  {
    "title":"NodeJs",
    "image":"/logos/nodejs.svg",
    "link":"https://nodejs.org/en/about/"
  },
  {
    "title":"Angular",
    "image":"/logos/angular.svg",
    "link":"https://angular.io/"
  },
  {
    "title":"Springboot",
    "image":"/logos/springio.svg",
    "link":"https://spring.io/"
  },
  {
    "title":"Svelte",
    "image":"/logos/svelte.svg",
    "link":"https://kit.svelte.dev/"
  },
  {
    "title":"Swagger",
    "image":"/logos/swagger.svg"
  }
]